pxsas.py
pxsas-1.1.dist-info/LICENSE
pxsas-1.1.dist-info/METADATA
pxsas-1.1.dist-info/WHEEL
pxsas-1.1.dist-info/top_level.txt
pxsas-1.1.dist-info/RECORD
